toolkit/__init__.py
toolkit/toolkit.py
pyaoponto_toolkit-0.1.1.dist-info/METADATA
pyaoponto_toolkit-0.1.1.dist-info/WHEEL
pyaoponto_toolkit-0.1.1.dist-info/RECORD
