Metadata-Version: 2.1
Name: pyaoponto-toolkit
Version: 0.1.1
Summary: A toolkit for python code
License: MIT
Author: Estevao Fonseca
Author-email: estevaopfon@gmail.com
Requires-Python: >=3.8,<4.0
Classifier: License :: OSI Approved :: MIT License
Classifier: Programming Language :: Python :: 3
Classifier: Programming Language :: Python :: 3.8
Classifier: Programming Language :: Python :: 3.9
Classifier: Programming Language :: Python :: 3.10
Classifier: Programming Language :: Python :: 3.11
Classifier: Programming Language :: Python :: 3.12
